{
  "project_info": {
    "project_number": "980857958762",
    "project_id": "flutter-chat-app-16526",
    "storage_bucket": "flutter-chat-app-16526.appspot.com"
  },
  "client": [
    {
      "client_info": {
        "mobilesdk_app_id": "1:980857958762:android:ca5bf103df1f200b9a3513",
        "android_client_info": {
          "package_name": "com.example.chat_app"
        }
      },
      "oauth_client": [],
      "api_key": [
        {
          "current_key": "AIzaSyBBLERlvjaSMNVQ1eoqpHcrM7t43gScc9E"
        }
      ],
      "services": {
        "appinvite_service": {
          "other_platform_oauth_client": []
        }
      }
    }
  ],
  "configuration_version": "1"
}